bijection.py
bijection-0.1.1.dist-info/DESCRIPTION.rst
bijection-0.1.1.dist-info/METADATA
bijection-0.1.1.dist-info/RECORD
bijection-0.1.1.dist-info/WHEEL
bijection-0.1.1.dist-info/metadata.json
bijection-0.1.1.dist-info/top_level.txt
