Metadata-Version: 2.0
Name: bijection
Version: 0.1.1
Summary: A library for producing bijective functions in Python.
Home-page: https://github.com/binarybirchtree/python-bijection
Author: Binary Birch Tree
Author-email: binarybirchtree@users.noreply.github.com
License: Apache License 2.0
Keywords: bijection bijective function
Platform: UNKNOWN
Classifier: Intended Audience :: Developers
Classifier: License :: OSI Approved :: Apache Software License
Classifier: Operating System :: OS Independent
Classifier: Programming Language :: Python :: 2
Classifier: Programming Language :: Python :: 2.7
Classifier: Programming Language :: Python :: 3
Classifier: Programming Language :: Python :: 3.5
Classifier: Topic :: Software Development
Requires-Dist: pycryptodome
